grill.pth
grill/__startup__/__init__.py
grill/__startup__/houdini.py
grill/__startup__/maya.py
grill/cook/__init__.py
grill/resources/houdini/MainMenuCommon.xml
grill/resources/houdini/package.json
grill/resources/usd/plugInfo.json
grill/usd/__init__.py
grill/views/_attributes.py
grill/views/_core.py
grill/views/_graph.py
grill/views/_launc_comp.py
grill/views/_launch_views.py
grill/views/_qt.py
grill/views/create.py
grill/views/description.py
grill/views/houdini.py
grill/views/maya.py
grill/views/sheets.py
grill/views/stats.py
grill/views/usdview.py
grill-0.19.1.dist-info/licenses/LICENSE
grill-0.19.1.dist-info/METADATA
grill-0.19.1.dist-info/WHEEL
grill-0.19.1.dist-info/top_level.txt
grill-0.19.1.dist-info/RECORD
