Metadata-Version: 2.4
Name: grill
Version: 0.19.1
Summary: Pipeline tools for (but not limited to) audiovisual projects.
Home-page: https://github.com/thegrill/grill
Author: Christian López Barrón
Author-email: chris.gfz@gmail.com
Keywords: cg cgi audiovisual pipeline tools usd pxr cook pixar 3d animation
Classifier: Programming Language :: Python :: 3.9
Classifier: Programming Language :: Python :: 3.10
Classifier: Programming Language :: Python :: 3.11
Classifier: Programming Language :: Python :: 3.12
Classifier: Programming Language :: Python :: 3.13
License-File: LICENSE
Requires-Dist: numpy
Requires-Dist: pydot>=3.0.1
Requires-Dist: networkx>=3.4; python_version > "3.9"
Requires-Dist: networkx<=2.8.3; python_version <= "3.9"
Provides-Extra: docs
Requires-Dist: sphinx; extra == "docs"
Requires-Dist: myst-parser; extra == "docs"
Requires-Dist: sphinx-toggleprompt; extra == "docs"
Requires-Dist: sphinx-copybutton; extra == "docs"
Requires-Dist: sphinx-togglebutton; extra == "docs"
Requires-Dist: sphinx-hoverxref>=1.4.1; extra == "docs"
Requires-Dist: sphinx_autodoc_typehints; extra == "docs"
Requires-Dist: sphinx-inline-tabs; extra == "docs"
Requires-Dist: shibuya; extra == "docs"
Requires-Dist: usd-core; extra == "docs"
Requires-Dist: sphinxcontrib-doxylink; extra == "docs"
Provides-Extra: full
Requires-Dist: PySide6; extra == "full"
Requires-Dist: usd-core; extra == "full"
Requires-Dist: PyOpenGL; extra == "full"
Provides-Extra: create
Requires-Dist: grill-names>=2.6.0; extra == "create"
Dynamic: license-file
